BatchTINTV3/__init__.py
BatchTINTV3/__main__.py
BatchTINTV3/main.py
BatchTINTV3/setup_exe.py
BatchTINTV3/core/ChooseDirectory.py
BatchTINTV3/core/__init__.py
BatchTINTV3/core/addSessions.py
BatchTINTV3/core/defaultParameters.py
BatchTINTV3/core/delete_temp.py
BatchTINTV3/core/klusta_functions.py
BatchTINTV3/core/klusta_utils.py
BatchTINTV3/core/settings.py
BatchTINTV3/core/smtpSettings.py
BatchTINTV3/core/utils.py
BatchTINTV3/img/GEBA_Logo.png
BatchTINTV3/img/__init__.py
BatchTINTV3-3.1.0.dist-info/LICENSE
BatchTINTV3-3.1.0.dist-info/METADATA
BatchTINTV3-3.1.0.dist-info/WHEEL
BatchTINTV3-3.1.0.dist-info/top_level.txt
BatchTINTV3-3.1.0.dist-info/RECORD
