Metadata-Version: 2.1
Name: BatchTINTV3
Version: 3.1.0
Summary: BatchTINTV3 - GUI created to more efficiently sort Axona/Tint data.
Home-page: https://github.com/HussainiLab/BatchTINTV3.git
Author: Geoffrey Barrett
Author-email: geoffrey.m.barrett@gmail.com
License: UNKNOWN
Platform: UNKNOWN
Classifier: Programming Language :: Python :: 3.7 
Classifier: License :: OSI Approved :: GNU General Public License v3 (GPLv3) 
Classifier: Operating System :: OS Independent
Requires-Dist: PyQt5
